flask_fastconfig/__init__.py
flask_fastconfig/config_opt.py
flask_fastconfig-0.0.3.dist-info/LICENSE
flask_fastconfig-0.0.3.dist-info/METADATA
flask_fastconfig-0.0.3.dist-info/WHEEL
flask_fastconfig-0.0.3.dist-info/top_level.txt
flask_fastconfig-0.0.3.dist-info/RECORD
