Metadata-Version: 2.1
Name: flask-fastconfig
Version: 0.0.3
Summary: ini config model for flask
Home-page: https://github.com/zpzhoudev/flask-fastconfig
Author: Zhou Zhiping
Author-email: himoker@163.com
License: UNKNOWN
Platform: UNKNOWN
Classifier: Programming Language :: Python :: 3
Classifier: License :: OSI Approved :: MIT License
Classifier: Operating System :: OS Independent
